<?xml version="1.0" encoding="UTF-8"?><artifacts>
    <artifact name="LocanaSellingsUpsert" groupId="com.loccana.selling.resource" version="1.0.0" type="registry/resource" serverRole="EnterpriseIntegrator">
        <item>
            <file>LocanaSellingsUpsert.json</file>
            <path>/_system/config/schema</path>
            <mediaType>application/json</mediaType>
            <properties/>
        </item>
    </artifact>
    <artifact name="CreateLoccanaSelllingInvoice" groupId="com.loccana.selling.resource" version="1.0.0" type="registry/resource" serverRole="EnterpriseIntegrator">
        <item>
            <file>CreateLoccanaSelllingInvoice.json</file>
            <path>/_system/config/schema</path>
            <mediaType>application/json</mediaType>
            <properties/>
        </item>
    </artifact>
    <artifact name="CreateLoccanaSellingReturn" groupId="com.loccana.selling.resource" version="1.0.0" type="registry/resource" serverRole="EnterpriseIntegrator">
        <item>
            <file>CreateLoccanaSellingReturn.json</file>
            <path>/_system/config/schema</path>
            <mediaType>application/json</mediaType>
            <properties/>
        </item>
    </artifact>
    <artifact name="CreateSellingHistory" groupId="com.loccana.selling.resource" version="1.0.0" type="registry/resource" serverRole="EnterpriseIntegrator">
        <item>
            <file>CreateSellingHistory.json</file>
            <path>/_system/config/schema</path>
            <mediaType>application/json</mediaType>
            <properties/>
        </item>
    </artifact>
    <artifact name="ListSelling" groupId="com.loccana.selling.resource" version="1.0.0" type="registry/resource" serverRole="EnterpriseIntegrator">
        <item>
            <file>ListSelling.json</file>
            <path>/_system/config/schema</path>
            <mediaType>application/json</mediaType>
            <properties/>
        </item>
    </artifact>
    </artifacts>
